wsinfer_mil/__init__.py
wsinfer_mil/__main__.py
wsinfer_mil/_version.py
wsinfer_mil/cache.py
wsinfer_mil/cli.py
wsinfer_mil/data.py
wsinfer_mil/defaults.py
wsinfer_mil/errors.py
wsinfer_mil/extractors.py
wsinfer_mil/inference.py
wsinfer_mil/output_container.py
wsinfer_mil/py.typed
wsinfer_mil/quickhash.py
wsinfer_mil/wsi_utils.py
wsinfer_mil/client/__init__.py
wsinfer_mil/client/hfmodel.py
wsinfer_mil/client/localmodel.py
wsinfer_mil/client/zoo.py
wsinfer_mil/patchlib/__init__.py
wsinfer_mil/patchlib/patch.py
wsinfer_mil/patchlib/segment.py
wsinfer_mil/schemas/model-config.schema.json
wsinfer_mil/schemas/wsinfer-mil-zoo-registry.schema.json
wsinfer_mil-0.1.0.dist-info/LICENSE
wsinfer_mil-0.1.0.dist-info/METADATA
wsinfer_mil-0.1.0.dist-info/WHEEL
wsinfer_mil-0.1.0.dist-info/entry_points.txt
wsinfer_mil-0.1.0.dist-info/top_level.txt
wsinfer_mil-0.1.0.dist-info/RECORD
