Metadata-Version: 2.1
Name: wsinfer-mil
Version: 0.1.0
Summary: Run specimen-level inference on whole slide images.
Author-email: Jakub Kaczmarzyk <jakub.kaczmarzyk@stonybrookmedicine.edu>
Maintainer-email: Jakub Kaczmarzyk <jakub.kaczmarzyk@stonybrookmedicine.edu>
License: Apache License, Version 2.0
Project-URL: Repository, https://github.com/SBU-BMI/wsinfer-mil
Project-URL: Bug Tracker, https://github.com/SBU-BMI/wsinfer-mil/issues
Classifier: Development Status :: 4 - Beta
Classifier: Environment :: Console
Classifier: Intended Audience :: Developers
Classifier: Intended Audience :: Healthcare Industry
Classifier: Intended Audience :: Science/Research
Classifier: License :: OSI Approved :: Apache Software License
Classifier: Operating System :: OS Independent
Classifier: Programming Language :: Python :: 3
Classifier: Programming Language :: Python :: 3 :: Only
Classifier: Programming Language :: Python :: 3.8
Classifier: Programming Language :: Python :: 3.9
Classifier: Programming Language :: Python :: 3.10
Classifier: Programming Language :: Python :: 3.11
Classifier: Programming Language :: Python :: 3.12
Classifier: Topic :: Scientific/Engineering :: Artificial Intelligence
Classifier: Topic :: Scientific/Engineering :: Image Recognition
Classifier: Topic :: Scientific/Engineering :: Medical Science Apps.
Requires-Python: >=3.8
License-File: LICENSE
Requires-Dist: click !=8.1.4,!=8.1.5,<9,>=8.0
Requires-Dist: h5py
Requires-Dist: huggingface-hub
Requires-Dist: jsonschema
Requires-Dist: numpy >=1.21.0
Requires-Dist: opencv-python-headless >=4.0.0
Requires-Dist: pillow
Requires-Dist: platformdirs
Requires-Dist: scikit-image >=0.20.0
Requires-Dist: shapely
Requires-Dist: tabulate
Requires-Dist: tifffile >=2023.1.23
Requires-Dist: tiffslide >=2.2.0
Requires-Dist: torch >=1.7
Requires-Dist: torchvision
Requires-Dist: tqdm
Requires-Dist: imagecodecs >=2022.7.27 ; python_version < "3.9"
Requires-Dist: imagecodecs >=2023.7.10 ; python_version >= "3.9"
Provides-Extra: dev
Requires-Dist: geojson ; extra == 'dev'
Requires-Dist: mypy ; extra == 'dev'
Requires-Dist: pre-commit ; extra == 'dev'
Requires-Dist: pytest ; extra == 'dev'
Requires-Dist: ruff ; extra == 'dev'
Requires-Dist: types-Pillow ; extra == 'dev'
Requires-Dist: types-tabulate ; extra == 'dev'
Requires-Dist: types-tqdm ; extra == 'dev'
Provides-Extra: docs
Requires-Dist: pydata-sphinx-theme ; extra == 'docs'
Requires-Dist: sphinx ; extra == 'docs'
Requires-Dist: sphinx-autoapi ; extra == 'docs'
Requires-Dist: sphinx-click ; extra == 'docs'
Requires-Dist: sphinx-copybutton ; extra == 'docs'
